pybind11_generics/__init__.py
pybind11_generics/_version.py
pybind11_generics/py.typed
pybind11_generics/build/__init__.py
pybind11_generics/stubgen/__init__.py
pybind11_generics/stubgen/__main__.py
pybind11_generics/stubgen/parsedoc.py
pybind11_generics/stubgen/stubgenc.py
pybind11_generics-1.0.3.dist-info/LICENSE
pybind11_generics-1.0.3.dist-info/METADATA
pybind11_generics-1.0.3.dist-info/WHEEL
pybind11_generics-1.0.3.dist-info/top_level.txt
pybind11_generics-1.0.3.dist-info/RECORD
