Metadata-Version: 2.1
Name: pybind11-generics
Version: 1.0.3
Summary: Python utilties for building C extensions created with pybind11_generics.
Home-page: UNKNOWN
Author: Eric Chang
Author-email: info@bcanalog.com
License: Apache-2.0
Platform: UNKNOWN
Requires-Python: >=3.9
License-File: LICENSE
Requires-Dist: packaging (>=20)
Requires-Dist: setuptools (>=50)
Requires-Dist: isort (>=5.7)
Requires-Dist: black (>=20.8b1)
Requires-Dist: click (>=7.1)
